{
  "generatedAt": "2025-11-29T03:37:03.908Z",
  "category": "Nagaland",
  "count": 2,
  "stations": [
    {
      "name": "Nagaland Christian Radio",
      "slug": "nagaland-christian-radio",
      "playerUrl": "https://www.radioindia.in/nagaland-christian-radio",
      "playerImage": "https://static.mytuner.mobi/media/radios-150px/4eu6kb3n2tsf.png",
      "description": "Listen to Nagaland Christian Radio online. Music, podcasts, shows and the latest news. FM Radio India, all stations.",
      "streams": [],
      "categories": [
        "Nagaland"
      ]
    },
    {
      "name": "Nagaland Christian Radio",
      "slug": "nagaland-christian-radio",
      "playerUrl": "https://www.radioindia.in/nagaland-christian-radio",
      "playerImage": "https://static.mytuner.mobi/media/radios-150px/4eu6kb3n2tsf.png",
      "description": "Listen to Nagaland Christian Radio online. Music, podcasts, shows and the latest news. FM Radio India, all stations.",
      "streams": [],
      "categories": [
        "Nagaland"
      ]
    }
  ]
}